{
  "version": "5.2.0.post4",
  "flags": {},
  "shapes": [
    {
      "label": "rider",
      "points": [
        [
          782.5714285714286,
          383.92857142857144
        ],
        [
          1382.5714285714287,
          1006.7857142857143
        ]
      ],
      "group_id": null,
      "description": "",
      "shape_type": "rectangle",
      "flags": {}
    },
    {
      "label": "helmet",
      "points": [
        [
          1031.1428571428573,
          395.3571428571429
        ],
        [
          1154.0,
          518.2142857142857
        ]
      ],
      "group_id": null,
      "description": "",
      "shape_type": "rectangle",
      "flags": {}
    }
  ],
  "imagePath": "..\\JPEGImages\\0969.jpg",
  "imageData": null,
  "imageHeight": 1365,
  "imageWidth": 2048
}