{
  "version": "5.2.0.post4",
  "flags": {},
  "shapes": [
    {
      "label": "rider",
      "points": [
        [
          705.4285714285714,
          143.92857142857144
        ],
        [
          1359.7142857142858,
          1292.5
        ]
      ],
      "group_id": null,
      "description": "",
      "shape_type": "rectangle",
      "flags": {}
    },
    {
      "label": "helmet",
      "points": [
        [
          1016.8571428571428,
          143.92857142857144
        ],
        [
          1245.4285714285716,
          383.92857142857144
        ]
      ],
      "group_id": null,
      "description": "",
      "shape_type": "rectangle",
      "flags": {}
    }
  ],
  "imagePath": "..\\JPEGImages\\1093.jpg",
  "imageData": null,
  "imageHeight": 1365,
  "imageWidth": 2048
}