{
  "version": "5.2.0.post4",
  "flags": {},
  "shapes": [
    {
      "label": "rider",
      "points": [
        [
          865.4285714285714,
          423.92857142857144
        ],
        [
          1188.2857142857144,
          923.9285714285714
        ]
      ],
      "group_id": null,
      "description": "",
      "shape_type": "rectangle",
      "flags": {}
    },
    {
      "label": "helmet",
      "points": [
        [
          968.2857142857142,
          426.78571428571433
        ],
        [
          1056.857142857143,
          512.5000000000001
        ]
      ],
      "group_id": null,
      "description": "",
      "shape_type": "rectangle",
      "flags": {}
    }
  ],
  "imagePath": "..\\JPEGImages\\1128.jpg",
  "imageData": null,
  "imageHeight": 1365,
  "imageWidth": 2048
}